uvlink/__init__.py
uvlink/cli.py
uvlink/project.py
uvlink-0.7.0.dist-info/WHEEL
uvlink-0.7.0.dist-info/entry_points.txt
uvlink-0.7.0.dist-info/METADATA
uvlink-0.7.0.dist-info/RECORD
