Metadata-Version: 2.3
Name: uvlink
Version: 0.7.0
Summary: CLI helper for keeping Python venvs outside synced project folders
Author: Cory Chu
Author-email: Cory Chu <cory@gwlab.page>
Classifier: Programming Language :: Python :: 3 :: Only
Classifier: Programming Language :: Python :: 3.12
Classifier: Programming Language :: Python :: 3.13
Classifier: Programming Language :: Python :: 3.14
Requires-Dist: rich>=14.2
Requires-Dist: typer>=0.20
Requires-Python: >=3.12
